bibl/.bibl.yml
bibl/__init__.py
bibl/__main__.py
bibl/config.py
bibl/lint.py
bibl/rule.py
bibl/text_utils.py
bibl/rules/__init__.py
bibl/rules/database_rules.py
bibl/rules/entry_rules.py
bibl/rules/field_rules.py
bibl/rules/specification_rules.py
bibl/rules/text_rules.py
bibL-1.0.4.dist-info/LICENSE
bibL-1.0.4.dist-info/METADATA
bibL-1.0.4.dist-info/WHEEL
bibL-1.0.4.dist-info/entry_points.txt
bibL-1.0.4.dist-info/top_level.txt
bibL-1.0.4.dist-info/RECORD
