Metadata-Version: 2.1
Name: bibL
Version: 1.0.4
Summary: A minimalistic bibtex linter
Home-page: https://gitlab.com/arne.vandenkerchove/biblint
Author: Arne Van Den Kerchove
Author-email: arne@vandenkerchove.com
License: MIT
Platform: UNKNOWN
Classifier: License :: OSI Approved :: MIT License
Classifier: Programming Language :: Python
Classifier: Programming Language :: Python :: 3
Classifier: Programming Language :: Python :: 3.7
Classifier: Operating System :: OS Independent
Requires-Dist: click (<8,>=7)
Requires-Dist: fuzzywuzzy (<1,>=0.10)
Requires-Dist: markdown-table
Requires-Dist: pybtex (==0.23.0)
Requires-Dist: pyyaml (<6,>=5)
Requires-Dist: unidecode (<2,>=1)
Provides-Extra: dev
Requires-Dist: flake8 ; extra == 'dev'
Requires-Dist: anybadge ; extra == 'dev'
Requires-Dist: markdown ; extra == 'dev'
Requires-Dist: check-manifest ; extra == 'dev'
Requires-Dist: twine ; extra == 'dev'
